anndata_metadata/__init__.py
anndata_metadata/__main__.py
anndata_metadata/extract.py
anndata_metadata/main.py
anndata_metadata-0.1.2.dist-info/METADATA
anndata_metadata-0.1.2.dist-info/WHEEL
anndata_metadata-0.1.2.dist-info/entry_points.txt
anndata_metadata-0.1.2.dist-info/top_level.txt
anndata_metadata-0.1.2.dist-info/RECORD
