Metadata-Version: 2.4
Name: anndata-metadata
Version: 0.1.2
Summary: Add your description here
Requires-Python: >=3.10
Requires-Dist: h5py>=3.13.0
Requires-Dist: pandas>=2.2.3
Requires-Dist: pyarrow>=20.0.0
Requires-Dist: s3fs>=2025.3.2
